pydatetime/__init__.py
pydatetime/pydatetime.py
pydatetime-1.3.dist-info/LICENSE
pydatetime-1.3.dist-info/METADATA
pydatetime-1.3.dist-info/WHEEL
pydatetime-1.3.dist-info/top_level.txt
pydatetime-1.3.dist-info/RECORD
